sphinx_modern_theme_modified/__init__.py
sphinx_modern_theme_modified/domainindex.html
sphinx_modern_theme_modified/genindex.html
sphinx_modern_theme_modified/page.html
sphinx_modern_theme_modified/search.html
sphinx_modern_theme_modified/theme.conf
sphinx_modern_theme_modified/static/doctools.js
sphinx_modern_theme_modified/static/documentation_options.js_t
sphinx_modern_theme_modified/static/jquery.js
sphinx_modern_theme_modified/static/searchtools.js
sphinx_modern_theme_modified/static/sphinx-modern-theme-modified.css
sphinx_modern_theme_modified/static/underscore.js
sphinx_modern_theme_modified/static/versions.js
sphinx_modern_theme_modified/static/websupport.js
sphinx_modern_theme_modified-1.0.4.dist-info/METADATA
sphinx_modern_theme_modified-1.0.4.dist-info/WHEEL
sphinx_modern_theme_modified-1.0.4.dist-info/top_level.txt
sphinx_modern_theme_modified-1.0.4.dist-info/RECORD
